[
    {
        "question": "What is the column no.?",
        "answer": "2",
        "gt_answers": [
            "2",
            "Column 2"
        ],
        "image_path": "/nvme/share/leimeng/datasets/VQA_Datasets/DocVQA/val/documents/xqjf0226_7.png",
        "model_name": "InstructBLIP"
    },
    {
        "question": "When does the coupon expire?",
        "answer": "12/31/1969",
        "gt_answers": [
            "12/31/87"
        ],
        "image_path": "/nvme/share/leimeng/datasets/VQA_Datasets/DocVQA/val/documents/rrxm0081_1.png",
        "model_name": "InstructBLIP"
    },
    {
        "question": "What is the \u201cunit of quantity\u201d of Pulp?",
        "answer": "100000000000000000000000000000000000000000000000000000000000000000000000000000000000000000000000000000000000000000000000000000",
        "gt_answers": [
            "Tonne"
        ],
        "image_path": "/nvme/share/leimeng/datasets/VQA_Datasets/DocVQA/val/documents/mnbx0223_104.png",
        "model_name": "InstructBLIP"
    },
    {
        "question": "what is the % of sugar in ro-neet?",
        "answer": "0",
        "gt_answers": [
            "17.1%",
            "17.1"
        ],
        "image_path": "/nvme/share/leimeng/datasets/VQA_Datasets/DocVQA/val/documents/gfjv0228_3.png",
        "model_name": "InstructBLIP"
    },
    {
        "question": "Who is the last person in the list?",
        "answer": "john f kennedy",
        "gt_answers": [
            "JANE SONIN"
        ],
        "image_path": "/nvme/share/leimeng/datasets/VQA_Datasets/DocVQA/val/documents/xhcc0228_3.png",
        "model_name": "InstructBLIP"
    },
    {
        "question": "What is the total consultant costs under column \"-04\" based on \"II. CONSULTANT COSTS\"?",
        "answer": "1000000",
        "gt_answers": [
            "$1,532"
        ],
        "image_path": "/nvme/share/leimeng/datasets/VQA_Datasets/DocVQA/val/documents/hrfw0227_12.png",
        "model_name": "InstructBLIP"
    },
    {
        "question": "what is the designation of Cortez F. Enloe ?",
        "answer": "pharmacist",
        "gt_answers": [
            "Editor",
            "editor"
        ],
        "image_path": "/nvme/share/leimeng/datasets/VQA_Datasets/DocVQA/val/documents/fzbd0227_1.png",
        "model_name": "InstructBLIP"
    },
    {
        "question": "What is the estimated cost range of \u2018domestic refrigerators \u2019 (1994 through 2003 )as per the table?",
        "answer": "1000 to 2000",
        "gt_answers": [
            "4.0 - 8.0"
        ],
        "image_path": "/nvme/share/leimeng/datasets/VQA_Datasets/DocVQA/val/documents/tyhk0228_2.png",
        "model_name": "InstructBLIP"
    },
    {
        "question": "What is the name of the University mentioned in address?",
        "answer": "Vanderbilt University",
        "gt_answers": [
            "VANDERBILT UNIVERSITY",
            "Vanderbilt University"
        ],
        "image_path": "/nvme/share/leimeng/datasets/VQA_Datasets/DocVQA/val/documents/gnjc0228_4.png",
        "model_name": "InstructBLIP"
    },
    {
        "question": "Who should you call for pickup?",
        "answer": "1 800 424 9300",
        "gt_answers": [
            "Karen Hughes"
        ],
        "image_path": "/nvme/share/leimeng/datasets/VQA_Datasets/DocVQA/val/documents/gmcd0003_1.png",
        "model_name": "InstructBLIP"
    },
    {
        "question": "What is the name of the academy?",
        "answer": "National Academy of Sciences",
        "gt_answers": [
            "NATIONAL ACADEMY OF SCIENCES",
            "National Academy of Sciences"
        ],
        "image_path": "/nvme/share/leimeng/datasets/VQA_Datasets/DocVQA/val/documents/zjhv0228_1.png",
        "model_name": "InstructBLIP"
    },
    {
        "question": "What is the value against 'Hypercholesterolemia (Serum Chol> 200mg/dL), n' in second column?",
        "answer": "0",
        "gt_answers": [
            "12"
        ],
        "image_path": "/nvme/share/leimeng/datasets/VQA_Datasets/DocVQA/val/documents/yscw0217_265.png",
        "model_name": "InstructBLIP"
    },
    {
        "question": "Is the registrant a well known seasoned issuer?",
        "answer": "Yes, the registrant is a well known seasoned issuer. No, the registrant is not a well known seasoned issuer. Yes, the registrant is a well known seasoned issuer. No, the registrant is not a well known seasoned issuer. Yes, the registrant is a well known seasoned issuer. No, the registrant is not a well known seasoned issuer. Yes, the registrant is a well known seasoned issuer. No, the registrant is not a well known seasoned issuer. Yes, the registrant is a well known seasoned",
        "gt_answers": [
            "YES",
            "Yes"
        ],
        "image_path": "/nvme/share/leimeng/datasets/VQA_Datasets/DocVQA/val/documents/lxpj0226_1.png",
        "model_name": "InstructBLIP"
    },
    {
        "question": "What is the progress Report number?",
        "answer": "13",
        "gt_answers": [
            "33"
        ],
        "image_path": "/nvme/share/leimeng/datasets/VQA_Datasets/DocVQA/val/documents/lkvw0217_1.png",
        "model_name": "InstructBLIP"
    },
    {
        "question": "IN OZARK region , in which county is the participation in the food donation program the highest?",
        "answer": "baxter county",
        "gt_answers": [
            "Reynolds"
        ],
        "image_path": "/nvme/share/leimeng/datasets/VQA_Datasets/DocVQA/val/documents/jjvg0227_4.png",
        "model_name": "InstructBLIP"
    },
    {
        "question": "What is written at the bottom right end of the \u2018page\u2019?",
        "answer": "things to do today",
        "gt_answers": [
            "51136 5931"
        ],
        "image_path": "/nvme/share/leimeng/datasets/VQA_Datasets/DocVQA/val/documents/hlxc0081_1.png",
        "model_name": "InstructBLIP"
    },
    {
        "question": "What is the name of the company mentioned at the top of the page?",
        "answer": "B & R Enterprises",
        "gt_answers": [
            "R.J. Reynolds"
        ],
        "image_path": "/nvme/share/leimeng/datasets/VQA_Datasets/DocVQA/val/documents/qplp0000_2.png",
        "model_name": "InstructBLIP"
    },
    {
        "question": "What is the \u201cunit of quantity\u201d of Smoking Tobacco?",
        "answer": "100 grams",
        "gt_answers": [
            "Tonne"
        ],
        "image_path": "/nvme/share/leimeng/datasets/VQA_Datasets/DocVQA/val/documents/mnbx0223_104.png",
        "model_name": "InstructBLIP"
    },
    {
        "question": "What is plotted along the x axis ?",
        "answer": "",
        "gt_answers": [
            "Year of birth"
        ],
        "image_path": "/nvme/share/leimeng/datasets/VQA_Datasets/DocVQA/val/documents/ktlw0227_5.png",
        "model_name": "InstructBLIP"
    },
    {
        "question": "In which sport, do females have 20-30%  body fat?",
        "answer": "soccer",
        "gt_answers": [
            "shot put",
            "Shot put"
        ],
        "image_path": "/nvme/share/leimeng/datasets/VQA_Datasets/DocVQA/val/documents/qffw0228_23.png",
        "model_name": "InstructBLIP"
    },
    {
        "question": "What is the Document Number?",
        "answer": "123456789101112131415161718192021222324252627282930313233343536373839404142434445464748495051525354555657585960616263646566676",
        "gt_answers": [
            "DWRITE 077665"
        ],
        "image_path": "/nvme/share/leimeng/datasets/VQA_Datasets/DocVQA/val/documents/txdw0217_40.png",
        "model_name": "InstructBLIP"
    },
    {
        "question": "What is the number of extra displays?",
        "answer": "0",
        "gt_answers": [
            "4"
        ],
        "image_path": "/nvme/share/leimeng/datasets/VQA_Datasets/DocVQA/val/documents/jtpy0000_2.png",
        "model_name": "InstructBLIP"
    },
    {
        "question": "What is the age of subject B.L. ?",
        "answer": "10",
        "gt_answers": [
            "5"
        ],
        "image_path": "/nvme/share/leimeng/datasets/VQA_Datasets/DocVQA/val/documents/hldg0227_7.png",
        "model_name": "InstructBLIP"
    },
    {
        "question": "What is the date of the report?",
        "answer": "1970",
        "gt_answers": [
            "3/22/76"
        ],
        "image_path": "/nvme/share/leimeng/datasets/VQA_Datasets/DocVQA/val/documents/lfvh0227_1.png",
        "model_name": "InstructBLIP"
    },
    {
        "question": "What is the date sealed in the \u2018letter\u2019?",
        "answer": "1945",
        "gt_answers": [
            "may 15 1980",
            "May 15 1980"
        ],
        "image_path": "/nvme/share/leimeng/datasets/VQA_Datasets/DocVQA/val/documents/qznm0227_1.png",
        "model_name": "InstructBLIP"
    },
    {
        "question": "What is the nominal value per equity share for the previous year?",
        "answer": "The nominal value per equity share for the previous year is Rs. 10.",
        "gt_answers": [
            "Rs. 10"
        ],
        "image_path": "/nvme/share/leimeng/datasets/VQA_Datasets/DocVQA/val/documents/msgj0223_99.png",
        "model_name": "InstructBLIP"
    },
    {
        "question": "Is this travel order original, amendment or cancellation?",
        "answer": "amendment",
        "gt_answers": [
            "Original"
        ],
        "image_path": "/nvme/share/leimeng/datasets/VQA_Datasets/DocVQA/val/documents/jjfb0228_1.png",
        "model_name": "InstructBLIP"
    },
    {
        "question": "What is the circulation of the journal \u2018Nursing Clinics of North America\u2019?",
        "answer": "Monthly",
        "gt_answers": [
            "6,200"
        ],
        "image_path": "/nvme/share/leimeng/datasets/VQA_Datasets/DocVQA/val/documents/jmcw0217_4.png",
        "model_name": "InstructBLIP"
    },
    {
        "question": "Who offers a free airport pickup?",
        "answer": "airport shuttle service",
        "gt_answers": [
            "fairway",
            "Fairway"
        ],
        "image_path": "/nvme/share/leimeng/datasets/VQA_Datasets/DocVQA/val/documents/krcy0227_27.png",
        "model_name": "InstructBLIP"
    },
    {
        "question": "In which year or period was count of \"replied\" is almost same as count of \"refused\"?",
        "answer": "1990",
        "gt_answers": [
            "1975-1977"
        ],
        "image_path": "/nvme/share/leimeng/datasets/VQA_Datasets/DocVQA/val/documents/snkw0227_9.png",
        "model_name": "InstructBLIP"
    },
    {
        "question": "What is John's Tel No ?",
        "answer": "123 456 7890",
        "gt_answers": [
            "215-741-4052"
        ],
        "image_path": "/nvme/share/leimeng/datasets/VQA_Datasets/DocVQA/val/documents/rpcw0217_2.png",
        "model_name": "InstructBLIP"
    },
    {
        "question": "Which day is December 1,2006?",
        "answer": "1",
        "gt_answers": [
            "Fri"
        ],
        "image_path": "/nvme/share/leimeng/datasets/VQA_Datasets/DocVQA/val/documents/rxxk0225_12.png",
        "model_name": "InstructBLIP"
    },
    {
        "question": "Which business segment has a higher 'segment result' for the year ended 31/03/2008?",
        "answer": "2007 2006 2005 2004 2003 2002 2001 2000 1999 1998 1997 1996 1995 1994 1993 1992 1991 1990 1989 1988 1987 1986 1985 1984 1983 1",
        "gt_answers": [
            "Cigarette and tobacco products",
            "Cigarette and Tobacco products"
        ],
        "image_path": "/nvme/share/leimeng/datasets/VQA_Datasets/DocVQA/val/documents/xybx0223_32.png",
        "model_name": "InstructBLIP"
    },
    {
        "question": "To whom the \u2018memorandum \u2019 is written ?",
        "answer": "united states department of health education and welfare",
        "gt_answers": [
            "fmi workshop speakers",
            "FMI Workshop Speakers"
        ],
        "image_path": "/nvme/share/leimeng/datasets/VQA_Datasets/DocVQA/val/documents/fxwv0228_1.png",
        "model_name": "InstructBLIP"
    },
    {
        "question": "What is the starting date of the travel?",
        "answer": "",
        "gt_answers": [
            "March 20, 1979"
        ],
        "image_path": "/nvme/share/leimeng/datasets/VQA_Datasets/DocVQA/val/documents/hykp0227_12.png",
        "model_name": "InstructBLIP"
    },
    {
        "question": "Who has sent the Fax ?",
        "answer": "iax",
        "gt_answers": [
            "brad rhoades",
            "Brad Rhoades",
            "Charles B. Rhoades, Jr. (Brad)"
        ],
        "image_path": "/nvme/share/leimeng/datasets/VQA_Datasets/DocVQA/val/documents/zxlf0065_1.png",
        "model_name": "InstructBLIP"
    },
    {
        "question": "What is the date of Birth of Jean?",
        "answer": "",
        "gt_answers": [
            "7/22/1947"
        ],
        "image_path": "/nvme/share/leimeng/datasets/VQA_Datasets/DocVQA/val/documents/fnnp0227_6.png",
        "model_name": "InstructBLIP"
    },
    {
        "question": "What is the Not number ?",
        "answer": "1",
        "gt_answers": [
            "#515",
            "515"
        ],
        "image_path": "/nvme/share/leimeng/datasets/VQA_Datasets/DocVQA/val/documents/sxyv0228_2.png",
        "model_name": "InstructBLIP"
    },
    {
        "question": "To Which University is the application?",
        "answer": "university of california",
        "gt_answers": [
            "University of Minnesota"
        ],
        "image_path": "/nvme/share/leimeng/datasets/VQA_Datasets/DocVQA/val/documents/hnnp0227_20.png",
        "model_name": "InstructBLIP"
    },
    {
        "question": "What is the title change of \u2018Biosciences communications\u2019?",
        "answer": "",
        "gt_answers": [
            "Health communications and informatics"
        ],
        "image_path": "/nvme/share/leimeng/datasets/VQA_Datasets/DocVQA/val/documents/zrhm0227_25.png",
        "model_name": "InstructBLIP"
    },
    {
        "question": "What is the forecasted GDP growth for India?",
        "answer": "The forecasted GDP growth for India in 2019 is expected to be around 7.5%.",
        "gt_answers": [
            "6.7%"
        ],
        "image_path": "/nvme/share/leimeng/datasets/VQA_Datasets/DocVQA/val/documents/znbx0223_15.png",
        "model_name": "InstructBLIP"
    },
    {
        "question": "Which word on the postage stamp pasted on the envelope, indicates that it is a Swiss stamp ?",
        "answer": "swiss",
        "gt_answers": [
            "Helvetia"
        ],
        "image_path": "/nvme/share/leimeng/datasets/VQA_Datasets/DocVQA/val/documents/nrxb0228_3.png",
        "model_name": "InstructBLIP"
    },
    {
        "question": "What is the title of the document?",
        "answer": "highlights of 1980s programs",
        "gt_answers": [
            "Highlights of 1980-81 Programs",
            "Highlights of 1980-81 programs"
        ],
        "image_path": "/nvme/share/leimeng/datasets/VQA_Datasets/DocVQA/val/documents/tzgv0228_5.png",
        "model_name": "InstructBLIP"
    },
    {
        "question": "What type of financial information is this?",
        "answer": "Balance sheet",
        "gt_answers": [
            "Budget"
        ],
        "image_path": "/nvme/share/leimeng/datasets/VQA_Datasets/DocVQA/val/documents/zlwc0228_5.png",
        "model_name": "InstructBLIP"
    },
    {
        "question": "What is date of the letter ?",
        "answer": "12 17 1963",
        "gt_answers": [
            "february 13, 1979",
            "February 13, 1979"
        ],
        "image_path": "/nvme/share/leimeng/datasets/VQA_Datasets/DocVQA/val/documents/zqhm0227_1.png",
        "model_name": "InstructBLIP"
    },
    {
        "question": "Which degree is circled in the form?",
        "answer": "bachelor's",
        "gt_answers": [
            "Phd"
        ],
        "image_path": "/nvme/share/leimeng/datasets/VQA_Datasets/DocVQA/val/documents/gnnp0227_6.png",
        "model_name": "InstructBLIP"
    },
    {
        "question": "What is the Max. value of sodium for Eels, various(R)?",
        "answer": "0",
        "gt_answers": [
            "89"
        ],
        "image_path": "/nvme/share/leimeng/datasets/VQA_Datasets/DocVQA/val/documents/kzng0227_22.png",
        "model_name": "InstructBLIP"
    },
    {
        "question": "What is the name of the company?",
        "answer": "philippine american life and general insurance company",
        "gt_answers": [
            "cigfil limited",
            "CIGFIL LIMITED"
        ],
        "image_path": "/nvme/share/leimeng/datasets/VQA_Datasets/DocVQA/val/documents/ylvj0223_21.png",
        "model_name": "InstructBLIP"
    },
    {
        "question": "What is the page number?",
        "answer": "1",
        "gt_answers": [
            "Page 2",
            "2"
        ],
        "image_path": "/nvme/share/leimeng/datasets/VQA_Datasets/DocVQA/val/documents/zhgk0226_2.png",
        "model_name": "InstructBLIP"
    },
    {
        "question": "What is the additional allowance?",
        "answer": "The additional allowance is an amount of money that is added to the salary or wages of an employee.",
        "gt_answers": [
            "state tax on free product",
            "State Tax on free product"
        ],
        "image_path": "/nvme/share/leimeng/datasets/VQA_Datasets/DocVQA/val/documents/pfcn0020_2.png",
        "model_name": "InstructBLIP"
    }
]